Lab08/ROM/ROM.v
//Este es el codigo para la memoria ROM

module ROM (
  input wire [11:0]address, //Las entradas de la memoria
  output wire [7:0]data); //Las salidas de la memoria

reg [7:0] ROM_m[0:4095]; //El tamaño de la memoria, palabra de 8 bits
//Profundidad de  2^12, es decir, 4096 localidades

initial begin
  $readmemh("ejemplo_ROM.list", ROM_m); //Se lee lo que hay en la memoria
end
assign data = ROM_m[address]; //Se extrae lo que hay en la dirrecion
//de la memoria y se le da un valor

endmodule //ROM

Lab08/ROM/ROM_tb.v
module testbenchROM ();
  reg [11:0]address;
  wire [7:0]data;

ROM Prueba(address, data);

initial begin
  #1
  $display("-------------------------");
  $display("-----------ROM-----------");
  $display("|   address       |          data  | ");
  $monitor("|      %b    |    %b   | ", address, data);

     address = 12'b000000000000;
  #1 address = 12'b000000000001;
  #1 address = 12'b000000000010;
  #1 address = 12'b000000000011;
  #1 address = 12'b000000000100;
  #1 address = 12'b000000000101;
  #1 address = 12'b000000000110;
  #1 address = 12'b000000000111;
  #1 address = 12'b000000001000;
  #1 address = 12'b000000001001;
end

initial
#21 $finish;

initial begin
  $dumpfile("ROM_tb.vcd");
  $dumpvars(0, testbenchROM);
end

endmodule //testbenchALU

Lab08/ROM/ROM_tb.vcd
$date
	Sat Oct 24 21:03:32 2020
$end
$version
	Icarus Verilog
$end
$timescale
	1ps
$end
$scope module testbenchROM $end
$var wire 8 ! data [7:0] $end
$var reg 12 " address [11:0] $end
$scope module Prueba $end
$var wire 12 # address [11:0] $end
$var wire 8 $ data [7:0] $end
$upscope $end
$upscope $end
$enddefinitions $end
#0
$dumpvars
bx $
bx #
bx "
bx !
$end
#1
b11001010 !
b11001010 $
b0 "
b0 #
#2
b11101111 !
b11101111 $
b1 "
b1 #
#3
b101011 !
b101011 $
b10 "
b10 #
#4
b1101001 !
b1101001 $
b11 "
b11 #
#5
b1 !
b1 $
b100 "
b100 #
#6
b10000 !
b10000 $
b101 "
b101 #
#7
b11101111 !
b11101111 $
b110 "
b110 #
#8
b11001010 !
b11001010 $
b111 "
b111 #
#9
b10111110 !
b10111110 $
b1000 "
b1000 #
#10
b11001010 !
b11001010 $
b1001 "
b1001 #
