Lab08/Contador/Contador.v
//Contador de 15 bits

module contador (
  input wire CLK, reset, En, LA, //En es el Enabled y LA es el bit que activa el Load.
  input wire [11:0]load,
  output reg [11:0]Out);

always @ (posedge CLK or posedge reset or LA or load)begin //El always se va a ejecutar si LA esta en 1 o 0
  if (reset) //El contador se pone en 0
    Out <= 12'b000000000000;

  else if (LA) //Permite que el valor de Load sea el valor con el que se quedó la salida
    Out <= load;

  else if (En) //Se inicia el conteo
    Out <= Out + 1;

end
endmodule //contador

Lab08/Contador/Contador_tb.v
module testebenchContador ();

reg CLK, reset, En, LA;
reg [11:0]load;
wire [11:0]out;

contador Co(CLK, reset, En, LA, load, out);

//Clock
always
  #1 CLK = ~CLK;

initial begin
#1
$display("-------------------------");
$display("----------Contador--------");
$display("|   CLK   |  reset  | Enable| Load activation | Load | out");
$monitor("    %b        %b        %b          %b           %b    %b ", CLK, reset, En, LA, load, out);
CLK = 0; reset = 0; En = 0; LA = 0; load = 12'b000000000000;
#1 reset = 0; //El contador no hace nada
#1 reset = 1; //El contador se pone en 0
#1 reset = 0;
#1 LA = 1; load = 12'b000010000000; //Se le pre carga un valor al Contador para iniciar desde alli
#1 LA = 0; En = 1; //empieza a contador
#1 En = 1;
end

initial
  #21 $finish ;

initial begin
  $dumpfile("Contador_tb.vcd");
  $dumpvars(0, testebenchContador);
end
endmodule //testebenchContador

Lab08/Contador/Contador_tb.vcd
$date
	Sat Oct 24 22:19:37 2020
$end
$version
	Icarus Verilog
$end
$timescale
	1ps
$end
$scope module testebenchContador $end
$var wire 12 ! out [11:0] $end
$var reg 1 " CLK $end
$var reg 1 # En $end
$var reg 1 $ LA $end
$var reg 12 % load [11:0] $end
$var reg 1 & reset $end
$scope module Co $end
$var wire 1 " CLK $end
$var wire 1 # En $end
$var wire 1 $ LA $end
$var wire 12 ' load [11:0] $end
$var wire 1 & reset $end
$var reg 12 ( Out [11:0] $end
$upscope $end
$upscope $end
$enddefinitions $end
#0
$dumpvars
bx (
bx '
x&
bx %
x$
x#
x"
bx !
$end
#1
b0 %
b0 '
0$
0#
0&
0"
#2
1"
#3
b0 !
b0 (
1&
0"
#4
0&
1"
#5
b10000000 !
b10000000 (
b10000000 %
b10000000 '
1$
0"
#6
b10000001 !
b10000001 (
1#
0$
1"
#7
0"
#8
b10000010 !
b10000010 (
1"
#9
0"
#10
b10000011 !
b10000011 (
1"
#11
0"
#12
b10000100 !
b10000100 (
1"
#13
0"
#14
b10000101 !
b10000101 (
1"
#15
0"
#16
b10000110 !
b10000110 (
1"
#17
0"
#18
b10000111 !
b10000111 (
1"
#19
0"
#20
b10001000 !
b10001000 (
1"
