Lab08/ALU/ALU.v
//programa para la ALU, por medio de casos se van a relizar las operaciones de la ALU
//--------------------------------FUNCIONES------------------------------------------
//  |000| Out = AND; |001| Out = OR; |010| Out = A + B; |011| Out = 0; |100| Out = A AND ~B;
// |101| Out = A OR ~B; |110| Out = A - B; |111| Out = SLT;

module ALU (
  input wire [3:0] A,B, //2 enttradas de 4-bit's
  input wire [2:0]Command, //3 bit's de funciones
  output reg [3:0]Out); //Salida de 3 bit's

  always @ (A or B or Command) begin

    //Aqui van los casos que tiene la ALU, segun cada operacion (se puede hasta 8 casos por la cantidad de bits en Command)
    case(Command)
      3'b000:Out = A & B; //Operacion AND
      3'b001:Out = A | B; //Operacion OR
      3'b010:Out = A + B; //Operacion suma
      3'b011:Out = 3'b000; //Esta operacion no hace nada
      3'b100:Out = A & ~B; //Operacion AND B negado
      3'b101:Out = A | ~B; //Operacion OR B negado
      3'b110:Out = A - B; //Operacion resta
      3'b111:Out = (A < B) ? 1:0; //Operacion comparacion de oposicion si A > B
      //default: Out = 3'b000; si se toma una opcion no asignada se da un valor de 0...
      //esto va a ser util cuando haya muchas mas funciones que no hagan nada

    endcase
  end

endmodule //ALU

Lab08/ALU/ALU_tb.v
module testbenchALU ();
  reg [3:0]A,B;
  reg [2:0]Command;
  wire [3:0]out;

ALU Prueba(A, B, Command, out);

initial begin
#1
$display("---------------------------------------");
$display("|   A  |   B  |   C  |  Result  |");
$monitor("|  %b  |  %b  |  %b  |  %b   |", A, B, Command, out);

   A = 4'b0001; B = 4'b0001; Command = 3'b000;
#1 A = 4'b0001; B = 4'b0001; Command = 3'b001;
#1 A = 4'b0001; B = 4'b0001; Command = 3'b010;
#1 A = 4'b0001; B = 4'b0001; Command = 3'b011;
#1 A = 4'b0001; B = 4'b0001; Command = 3'b100;
#1 A = 4'b0001; B = 4'b0001; Command = 3'b101;
#1 A = 4'b0001; B = 4'b0001; Command = 3'b110;
#1 A = 4'b0001; B = 4'b0001; Command = 3'b111;
end

initial
#21 $finish;

initial begin
  $dumpfile("ALU_tb.vcd");
  $dumpvars(0, testbenchALU);
end

endmodule //testbenchALU

Lab08/ALU/ALU_tb.vcd
$date
	Sat Oct 24 20:38:47 2020
$end
$version
	Icarus Verilog
$end
$timescale
	1ps
$end
$scope module testbenchALU $end
$var wire 4 ! out [3:0] $end
$var reg 4 " A [3:0] $end
$var reg 4 # B [3:0] $end
$var reg 3 $ Command [2:0] $end
$scope module Prueba $end
$var wire 4 % A [3:0] $end
$var wire 4 & B [3:0] $end
$var wire 3 ' Command [2:0] $end
$var reg 4 ( Out [3:0] $end
$upscope $end
$upscope $end
$enddefinitions $end
#0
$dumpvars
bx (
bx '
bx &
bx %
bx $
bx #
bx "
bx !
$end
#1
b1 !
b1 (
b0 $
b0 '
b1 #
b1 &
b1 "
b1 %
#2
b1 $
b1 '
#3
b10 !
b10 (
b10 $
b10 '
#4
b0 !
b0 (
b11 $
b11 '
#5
b100 $
b100 '
#6
b1111 !
b1111 (
b101 $
b101 '
#7
b0 !
b0 (
b110 $
b110 '
#8
b111 $
b111 '
