Lab09/Flip-flop tipo T/FF_T.v
//modulo de Flip flop tipo D de 1 bit
module FF_D (input D, CLK, En, reset,
  output reg Q);

always @ (posedge CLK or posedge reset) begin //cambia con valores positivos
  if (reset)
    Q <=  1'b0; //El valor de Q se pone en 0
 else if (En)
    Q <= D;
end
endmodule //FF_D1


module FF_T (
input wire  CLK, En, reset,
output wire Q);

FF_D FFT (~Q, CLK, En, reset, Q); //La entrada D es la salida Q, pero negada
endmodule //FF_T

Lab09/Flip-flop tipo T/FF_T_tb.v
module testbench ();

//flip flop de un bit
reg CLK, EN, reset;
wire Q;

FF_T FFT(CLK, EN, reset, Q); //El modulo solo tiene 3 entradas


initial begin
#1
  $display(" CLK | EN | reset | Q");
  $display("---------------------");
  $monitor("%b   | %b | %b    | %b|" , CLK, EN, reset, Q); 

  //entradas de los FF
  CLK = 0; EN = 0; reset = 0;
  #1 reset = 1;
  #1 reset = 0;
  #2 EN = 1;
  #1 EN = 0;
  #1 EN = 1;
  #1 EN = 0;
  #1 EN = 1;
  #3 EN = 0;
end
always
#1 CLK = ~CLK;

initial
  #20 $finish;

initial begin
  $dumpfile("FF_T_tb.vcd");
  $dumpvars(0,testbench);
end

endmodule //testbench

Lab09/Flip-flop tipo T/FF_D_tb.vcd
$date
	Sat Oct 31 09:41:51 2020
$end
$version
	Icarus Verilog
$end
$timescale
	1ps
$end
$scope module testbench $end
$var wire 1 ! Q $end
$var reg 1 " CLK $end
$var reg 1 # EN $end
$var reg 1 $ reset $end
$scope module FFT $end
$var wire 1 " CLK $end
$var wire 1 # En $end
$var wire 1 $ reset $end
$var wire 1 ! Q $end
$scope module FFT $end
$var wire 1 " CLK $end
$var wire 1 % D $end
$var wire 1 # En $end
$var wire 1 $ reset $end
$var reg 1 ! Q $end
$upscope $end
$upscope $end
$upscope $end
$enddefinitions $end
#0
$dumpvars
x%
x$
x#
x"
x!
$end
#1
0$
0#
1"
#2
1%
0!
0"
1$
#3
1"
0$
#4
0"
1#
#5
0%
1!
1"
#6
0"
#7
1%
0!
1"
#8
0"
#9
1"
0#
