Lab10/Ejercicio1/Ejercicio1.v
//CONTADOR
module contador (
  input wire CLK, reset, En, LA, //En es el Enabled y LA es el bit que activa el Load.
  input wire [11:0]load,
  output reg [11:0]Out);

always @ (posedge CLK or posedge reset or LA or load)begin //El always se va a ejecutar si LA esta en 1 o 0
    if (reset) //El contador se pone en 0
      Out <= 12'b000000000000;
    else if (LA) //Permite que se le diga en que valor empezar
      Out <= load;
    else if (En) //Se inicia el conteo
      Out <= Out + 1;
  end
endmodule //CONTADOR



//PARA ROM
module ROM(
  input wire [11:0]address, //Las entradas de la memoria
  output wire [7:0]data); //Las salidas de la memoria

reg [7:0] ROM_m[0:4095]; //El tamaño de la memoria, palabra de 8 bits
//Profundidad de  2^12, es decir, 4096 localidades

initial begin
  $readmemh("ejercicio1.procesador", ROM_m); //Se lee lo que hay en la memoria
end
assign data = ROM_m[address]; //Se extrae lo que hay en la dirrecion
//de la memoria y se le da un valor

endmodule //ROM



//ESTO ES SOLO PARA EL FETCH
module FFD(input wire clk, reset, En, D, output reg Q);

    always@(posedge clk or posedge reset) begin
        if(reset)
            Q <= 1'b0;
        else if (En)
            Q <= D;
    end
endmodule

//dos bits
module FFD2(input wire clk, reset, En,
            input wire [1:0]D2,
            output wire [1:0]Q2);

    FFD a(clk, reset, En, D2[1], Q2[1]);
    FFD b(clk, reset, En, D2[0], Q2[0]);
endmodule

//cuatro bits
module FFD4(input wire clk, reset, En,
            input wire [3:0]D4,
            output wire [3:0]Q4);

    FFD2 a(clk, reset, En, D4[3:2], Q4[3:2]);
    FFD2 b(clk, reset, En, D4[1:0], Q4[1:0]);
endmodule

//8 bits con entrada de 8 y dos salidas de 4
module Fetch(input wire clk, reset, En,
            input wire [7:0]D8,
            output wire [3:0]Q8a,
            output wire [3:0]Q8b);
    FFD4 a(clk, reset, En, D8[7:4], Q8a);
    FFD4 b(clk, reset, En, D8[3:0], Q8b);
endmodule


//MODULO PARA UNIR LOS MODULOS
module ejercicio1 (
  input wire clk, RESET ,ENC, ENload, ENF,
  input wire [11:0]Load,
  output wire [3:0]instr,
  output wire [3:0]oprnd,
  output wire [7:0]program_byte);

    wire [11:0]PC;

    contador C1(clk, RESET, ENC, ENload, Load, PC);
    ROM R1(PC, program_byte);
    Fetch FET(clk, RESET, ENF, program_byte, instr, oprnd);
endmodule //ejercicio1

Lab10/Ejercicio1/Ejercicio1_tb.v
module testbench ();
  reg CLK, Reset, EN_PC, EN_Fetch, ENload;
  reg [11:0]load;
  wire [7:0]program_byte;
  wire [3:0]instr;
  wire [3:0]oprnd;

  ejercicio1 test(CLK, Reset, EN_PC, EN_Fetch, ENload, load, instr, oprnd, program_byte);

  always
  #1 CLK = ~CLK;

  initial begin
    #1
    $display("--------------------------------Ejercicio 1----------------------------");
    $display("|  CLK | RESET | EN_PC  | EN_Fetch | ENload| LOAD            | instr |oprnd | program_byte");
    $monitor("|  %b   |  %b    |  %b   | %b   | %b     | %b   | %b    |  %b  |  %b       ", CLK, Reset, EN_PC, EN_Fetch, ENload, load, instr, oprnd, program_byte);

       CLK = 0; Reset = 1; EN_PC = 0; ENload = 0; EN_Fetch = 0; load = 12'b000000000000;
    #2 Reset = 0; EN_PC = 1; EN_Fetch = 1; ENload = 0;
    #2 Reset = 0; EN_PC = 1; EN_Fetch = 1; ENload = 0;
    #2 Reset = 0; EN_PC = 1; EN_Fetch = 1; ENload = 1; load = 12'b000000000100; //carga lo que esta en la localidad 4 (0100)
    #2 Reset = 0; EN_PC = 1; EN_Fetch = 1; ENload = 0;
    #2 Reset = 0; EN_PC = 1; EN_Fetch = 1; ENload = 1; load = 12'b000000001000;
    end


    initial
      #15 $finish;

    initial begin
      $dumpfile("Ejercicio1_tb.vcd");
      $dumpvars(0,testbench);
    end

endmodule //testbench

Lab10/Ejercicio1/Ejercicio1_tb.vcd
$date
	Sat Nov 07 21:43:50 2020
$end
$version
	Icarus Verilog
$end
$timescale
	1ps
$end
$scope module testbench $end
$var wire 8 ! program_byte [7:0] $end
$var wire 4 " oprnd [3:0] $end
$var wire 4 # instr [3:0] $end
$var reg 1 $ CLK $end
$var reg 1 % EN_Fetch $end
$var reg 1 & EN_PC $end
$var reg 1 ' ENload $end
$var reg 1 ( Reset $end
$var reg 12 ) load [11:0] $end
$scope module test $end
$var wire 1 & ENC $end
$var wire 1 ' ENF $end
$var wire 1 % ENload $end
$var wire 12 * Load [11:0] $end
$var wire 1 ( RESET $end
$var wire 1 $ clk $end
$var wire 8 + program_byte [7:0] $end
$var wire 4 , oprnd [3:0] $end
$var wire 4 - instr [3:0] $end
$var wire 12 . PC [11:0] $end
$scope module C1 $end
$var wire 1 $ CLK $end
$var wire 1 & En $end
$var wire 1 % LA $end
$var wire 12 / load [11:0] $end
$var wire 1 ( reset $end
$var reg 12 0 Out [11:0] $end
$upscope $end
$scope module FET $end
$var wire 1 ' En $end
$var wire 1 $ clk $end
$var wire 1 ( reset $end
$var wire 4 1 Q8b [3:0] $end
$var wire 4 2 Q8a [3:0] $end
$var wire 8 3 D8 [7:0] $end
$scope module a $end
$var wire 4 4 D4 [3:0] $end
$var wire 1 ' En $end
$var wire 1 $ clk $end
$var wire 1 ( reset $end
$var wire 4 5 Q4 [3:0] $end
$scope module a $end
$var wire 2 6 D2 [1:0] $end
$var wire 1 ' En $end
$var wire 1 $ clk $end
$var wire 1 ( reset $end
$var wire 2 7 Q2 [1:0] $end
$scope module a $end
$var wire 1 8 D $end
$var wire 1 ' En $end
$var wire 1 $ clk $end
$var wire 1 ( reset $end
$var reg 1 9 Q $end
$upscope $end
$scope module b $end
$var wire 1 : D $end
$var wire 1 ' En $end
$var wire 1 $ clk $end
$var wire 1 ( reset $end
$var reg 1 ; Q $end
$upscope $end
$upscope $end
$scope module b $end
$var wire 2 < D2 [1:0] $end
$var wire 1 ' En $end
$var wire 1 $ clk $end
$var wire 1 ( reset $end
$var wire 2 = Q2 [1:0] $end
$scope module a $end
$var wire 1 > D $end
$var wire 1 ' En $end
$var wire 1 $ clk $end
$var wire 1 ( reset $end
$var reg 1 ? Q $end
$upscope $end
$scope module b $end
$var wire 1 @ D $end
$var wire 1 ' En $end
$var wire 1 $ clk $end
$var wire 1 ( reset $end
$var reg 1 A Q $end
$upscope $end
$upscope $end
$upscope $end
$scope module b $end
$var wire 4 B D4 [3:0] $end
$var wire 1 ' En $end
$var wire 1 $ clk $end
$var wire 1 ( reset $end
$var wire 4 C Q4 [3:0] $end
$scope module a $end
$var wire 2 D D2 [1:0] $end
$var wire 1 ' En $end
$var wire 1 $ clk $end
$var wire 1 ( reset $end
$var wire 2 E Q2 [1:0] $end
$scope module a $end
$var wire 1 F D $end
$var wire 1 ' En $end
$var wire 1 $ clk $end
$var wire 1 ( reset $end
$var reg 1 G Q $end
$upscope $end
$scope module b $end
$var wire 1 H D $end
$var wire 1 ' En $end
$var wire 1 $ clk $end
$var wire 1 ( reset $end
$var reg 1 I Q $end
$upscope $end
$upscope $end
$scope module b $end
$var wire 2 J D2 [1:0] $end
$var wire 1 ' En $end
$var wire 1 $ clk $end
$var wire 1 ( reset $end
$var wire 2 K Q2 [1:0] $end
$scope module a $end
$var wire 1 L D $end
$var wire 1 ' En $end
$var wire 1 $ clk $end
$var wire 1 ( reset $end
$var reg 1 M Q $end
$upscope $end
$scope module b $end
$var wire 1 N D $end
$var wire 1 ' En $end
$var wire 1 $ clk $end
$var wire 1 ( reset $end
$var reg 1 O Q $end
$upscope $end
$upscope $end
$upscope $end
$upscope $end
$scope module R1 $end
$var wire 12 P address [11:0] $end
$var wire 8 Q data [7:0] $end
$upscope $end
$upscope $end
$upscope $end
$enddefinitions $end
#0
$dumpvars
bx Q
bx P
xO
xN
xM
xL
bx K
bx J
xI
xH
xG
xF
bx E
bx D
bx C
bx B
xA
x@
x?
x>
bx =
bx <
x;
x:
x9
x8
bx 7
bx 6
bx 5
bx 4
bx 3
bx 2
bx 1
bx 0
bx /
bx .
bx -
bx ,
bx +
bx *
bx )
x(
x'
x&
x%
x$
bx #
bx "
bx !
$end
#1
1F
0H
1L
1N
18
1:
0>
0@
b10 D
b11 J
b11 6
b0 <
b1011 B
b1100 4
b11001011 !
b11001011 +
b11001011 3
b11001011 Q
b0 .
b0 0
b0 P
09
b0 7
0;
0?
b0 #
b0 -
b0 2
b0 5
b0 =
0A
0G
b0 E
0I
0M
b0 "
b0 ,
b0 1
b0 C
b0 K
0O
b0 )
b0 *
b0 /
0%
0'
0&
1(
0$
#2
1$
#3
0$
1%
1&
0(
#4
1$
#5
0$
#6
1$
#7
0F
1H
0N
08
0:
b1 D
b10 J
b0 6
b110 B
b0 4
b110 !
b110 +
b110 3
b110 Q
b100 .
b100 0
b100 P
0$
b100 )
b100 *
b100 /
1'
#8
b1 E
1I
b110 "
b110 ,
b110 1
b110 C
b10 K
1M
1$
#9
0$
0'
#10
1$
#11
0H
b0 D
b10 B
b10 !
b10 +
b10 3
b10 Q
b1000 .
b1000 0
b1000 P
0$
b1000 )
b1000 *
b1000 /
1'
#12
b10 "
b10 ,
b10 1
b10 C
b0 E
0I
1$
