lab04/lab04.v
//En esta parte se implementan todas las ecuaciones con gate label modeling

//Ecuación implementada Y = (A'*C')+(A*C)+(A*B');
module Ejercicio1_tabla1 (input wire A, B, C, output wire Y);

wire NA, NB, NC, W1, W2, W3; //Tres cables not  y tres grupos and

//funciones logicas

//Ecuación a implentar Y = (A'*C')+(B'*C')+(A*C);
not(NA, A); //las primeras tres son solo para negar las tres entradas
not(NB, B);
not(NC, C);
and(W1, NA, NC);
and(W2, NB, NC);
and(W3, A, C);
or (Y, W1, W2, W3); //salida

endmodule //Ejercicio1_tabla1

//Ecuación a implementar Y= B';
module Ejercicio1_tabla2 (input wire A, B, C, output wire Y);

//función lógica

not(Y, B); //no hubo necedidad de crear un cable extra, solo el de salida

endmodule //Ejercicio1_tabla2

//Ecuación a implentar Y = (A'*B'*C'*D')+(A'*B'*C*D)+(A'*B*C'*D)...
//+(A'*B*C*D')+(A*B*C'*D')+(A*B*C*D)+(A*B'*C*D)+(A*B'*C*D');

module Ejercicio1_tabla3 (input wire A, B, C, D, output wire Y);

wire NA, NB, NC, ND, W1, W2, W3, W4, W5, W6, W7, W8; //Cuatro cables de not y 8 cables and

//funciones logicas

not(NA, A);
not(NB, B);
not(NC, C);
not(ND, D);
and(W1, NA, NB, NC, ND);
and(W2, NA, NB, C, D);
and(W3, NA, B, NC, D);
and(W4, NA, B, C, ND);
and(W5, A, B, NC, ND);
and(W6, A, B, C, D);
and(W7, A, NB, NC, D);
and(W8, A, NB, C, ND);
or(Y, W1, W2, W3, W4, W5, W6, W7, W8);

endmodule //Ejercicio1_tabla3

//Ecuación a implentar Y = (B'*D')+(A*B)+(A*C);

module Ejercicio1_tabla4 (input wire A, B, C, D, output wire Y);

//funciines logicas

wire NB, ND, W1, W2, W3; //Dos cables not y 3 cables and

not(NB, B);
not(ND, D);
and(W1, NB, ND);
and(W2, A, B);
and(W3, A, C);
or(Y, W1, W2, W3);

endmodule //Ejercicio1_tabla4

//En esta parte se implementan todas las ecuaciones con operadores lógicos

// Ecuación a implentar Y = (B'*C'*D')+(A*C')+(A*D')+(A*B');
module Ejercicio2_tabla1 (input wire A, B, C, D, output wire Y);

  assign Y = (~B & ~C & ~D) | (A & ~C) | (A & ~D) | (A & ~B);

endmodule // Ejercicio2_tabla1

//Ecuación a implentar Y = C + B';
module Ejercicio2_tabla2 (input wire A, B, C, output wire Y);

  assign Y = (C) | (~B);

endmodule // Ejercicio2_tabla2

//Ecuación a implementar Y = B + (C'*D) + (A*D);
module Ejercicio2_tabla3 (input wire A, B, C, D, output wire Y);

  assign Y = (B) | (~C & D) | (A & D);

endmodule // Ejercicio2_tabla3

//Ecuación a implentar Y = B + (A'*C');
module Ejercicio2_tabla4 (input wire A, B, C, output wire Y);

  assign Y = (B) | (~A & ~C);

endmodule // Ejercicio2_tabla4

lab04/lab04_tb.v
module testebench();

//Se van a reutilizar algunas variables en bloques de 2 en 2
reg p1, p2, p3, p4, p5, p6, p7; //Estos son para las primeras 4 tablas
wire out1, out2, out3, out4; //Son las salidas de las primeras 4 tablas
reg p8, p9, p10, p11, p12, p13, p14; //Estos son para las 4 tablas del ejercicio 2
wire out5, out6, out7, out8; //Salidas de las cuatro tablas del ejercicio 2

//Ejercicio 1, tabla01 y tabla02
Ejercicio1_tabla1 G1(p1, p2, p3, out1);
Ejercicio1_tabla2 G2(p1, p2, p3, out2);

initial begin
#1
$display("Tabla 1 y 2 de ejercicio 01");
$display("A B C | Y1 Y2");
$display("------|------");
$monitor("%b %b %b | %b %b", p1, p2, p3, out1, out2);
     p1 = 0; p2 = 0; p3 = 0;
  #1 p3 = 1;
  #1 p2 = 1; p3 = 0;
  #1 p3 = 1;
  #1 p1 = 1; p2 = 0; p3 = 0;
  #1 p3 = 1;
  #1 p2 = 1; p3 =0;
  #1 p3 = 1;
end

//Ejercicio 1, tabla03 y tabla04
Ejercicio1_tabla3 G3(p4, p5, p6, p7, out3);
Ejercicio1_tabla4 G4(p4, p5, p6, p7, out4);

initial begin
#9
$display("\n");
$display("Tabla 3 y 4 de ejercicio 01");
$display("A B C D | Y1 Y2");
$display("--------|------");
$monitor("%b %b %b %b | %b %b", p4, p5, p6, p7, out3, out4);
     p4 = 0; p5 = 0; p6 = 0; p7 = 0;
  #1 p7 = 1;
  #1 p6 = 1; p7 = 0;
  #1 p7 = 1;
  #1 p5 = 1; p6 = 0; p7 = 0;
  #1 p7 = 1;
  #1 p6 = 1; p7 = 0;
  #1 p7 = 1;
  #1 p4 = 1; p5 = 0; p6 = 0; p7 =0;
  #1 p7 = 1;
  #1 p6 = 1; p7 = 0;
  #1 p7 = 1;
  #1 p5 = 1; p6 = 0; p7 = 0;
  #1 p7 = 1;
  #1 p6 = 1; p7 = 0;
  #1 p7 = 1;
end

//Ejerercicio 2, ecuación 1 y 3
Ejercicio2_tabla1 OP1(p8, p9, p10, p11, out5);
Ejercicio2_tabla3 OP3(p8, p9, p10, p11, out6);

initial begin
#25
$display("\n");
$display("Tabla 1 y 3 de ejercicio 02");
$display("A B C D | Y1 Y2");
$display("------|------");
$monitor("%b %b %b %b | %b %b", p8, p9, p10, p11, out5, out6);
     p8 = 0; p9 = 0; p10 = 0; p11 = 0; //p4 p5 p6 p7
  #1 p11 = 1;
  #1 p10 = 1; p11 = 0;
  #1 p11 = 1;
  #1 p9 = 1; p10 = 0; p11 = 0;
  #1 p11 = 1;
  #1 p10 = 1; p11 = 0;
  #1 p11 = 1;
  #1 p8 = 1; p9 = 0; p10 = 0; p11 =0;
  #1 p11 = 1;
  #1 p10 = 1; p11 = 0;
  #1 p11 = 1;
  #1 p9 = 1; p10 = 0; p11 = 0;
  #1 p11 = 1;
  #1 p10 = 1; p11 = 0;
  #1 p11 = 1;
end

//Ejercicio 2, tabla02 y tabla04
Ejercicio2_tabla2 OP2(p12, p13, p14, out7);
Ejercicio2_tabla4 OP4(p12, p13, p14, out8);

initial begin
#41
$display("\n");
$display("Tabla 2 y 4 de ejercicio 02");
$display("A B C | Y1 Y2");
$display("------|------");
$monitor("%b %b %b | %b %b", p12, p13, p14, out7, out8);
     p12 = 0; p13 = 0; p14 = 0;
  #1 p14 = 1;
  #1 p13 = 1; p14 = 0;
  #1 p14 = 1;
  #1 p12 = 1; p13 = 0; p14 = 0;
  #1 p14 = 1;
  #1 p13 = 1; p14 =0;
  #1 p14 = 1;
end

initial
  #49 $finish;

  initial begin
    $dumpfile("lab04_tb.vcd");
    $dumpvars(0, testebench);
  end

endmodule

lab04/lab04_tb.vcd
$date
	Sat Aug 08 20:48:45 2020
$end
$version
	Icarus Verilog
$end
$timescale
	1ps
$end
$scope module testebench $end
$var wire 1 ! out8 $end
$var wire 1 " out7 $end
$var wire 1 # out6 $end
$var wire 1 $ out5 $end
$var wire 1 % out4 $end
$var wire 1 & out3 $end
$var wire 1 ' out2 $end
$var wire 1 ( out1 $end
$var reg 1 ) p1 $end
$var reg 1 * p10 $end
$var reg 1 + p11 $end
$var reg 1 , p12 $end
$var reg 1 - p13 $end
$var reg 1 . p14 $end
$var reg 1 / p2 $end
$var reg 1 0 p3 $end
$var reg 1 1 p4 $end
$var reg 1 2 p5 $end
$var reg 1 3 p6 $end
$var reg 1 4 p7 $end
$var reg 1 5 p8 $end
$var reg 1 6 p9 $end
$scope module G1 $end
$var wire 1 ) A $end
$var wire 1 / B $end
$var wire 1 0 C $end
$var wire 1 7 NA $end
$var wire 1 8 NB $end
$var wire 1 9 NC $end
$var wire 1 : W1 $end
$var wire 1 ; W2 $end
$var wire 1 < W3 $end
$var wire 1 ( Y $end
$upscope $end
$scope module G2 $end
$var wire 1 ) A $end
$var wire 1 / B $end
$var wire 1 0 C $end
$var wire 1 ' Y $end
$upscope $end
$scope module G3 $end
$var wire 1 1 A $end
$var wire 1 2 B $end
$var wire 1 3 C $end
$var wire 1 4 D $end
$var wire 1 = NA $end
$var wire 1 > NB $end
$var wire 1 ? NC $end
$var wire 1 @ ND $end
$var wire 1 A W1 $end
$var wire 1 B W2 $end
$var wire 1 C W3 $end
$var wire 1 D W4 $end
$var wire 1 E W5 $end
$var wire 1 F W6 $end
$var wire 1 G W7 $end
$var wire 1 H W8 $end
$var wire 1 & Y $end
$upscope $end
$scope module G4 $end
$var wire 1 1 A $end
$var wire 1 2 B $end
$var wire 1 3 C $end
$var wire 1 4 D $end
$var wire 1 I NB $end
$var wire 1 J ND $end
$var wire 1 K W1 $end
$var wire 1 L W2 $end
$var wire 1 M W3 $end
$var wire 1 % Y $end
$upscope $end
$scope module OP1 $end
$var wire 1 5 A $end
$var wire 1 6 B $end
$var wire 1 * C $end
$var wire 1 + D $end
$var wire 1 $ Y $end
$upscope $end
$scope module OP2 $end
$var wire 1 , A $end
$var wire 1 - B $end
$var wire 1 . C $end
$var wire 1 " Y $end
$upscope $end
$scope module OP3 $end
$var wire 1 5 A $end
$var wire 1 6 B $end
$var wire 1 * C $end
$var wire 1 + D $end
$var wire 1 # Y $end
$upscope $end
$scope module OP4 $end
$var wire 1 , A $end
$var wire 1 - B $end
$var wire 1 . C $end
$var wire 1 ! Y $end
$upscope $end
$upscope $end
$enddefinitions $end
#0
$dumpvars
xM
xL
xK
xJ
xI
xH
xG
xF
xE
xD
xC
xB
xA
x@
x?
x>
x=
x<
x;
x:
x9
x8
x7
x6
x5
x4
x3
x2
x1
x0
x/
x.
x-
x,
x+
x*
x)
x(
x'
x&
x%
x$
x#
x"
x!
$end
#1
1(
1;
1:
19
18
1'
17
0<
00
0/
0)
#2
0(
0:
0;
09
10
#3
1(
1:
19
08
0'
00
1/
#4
0(
0:
09
10
#5
1(
1;
19
18
1'
07
00
0/
1)
#6
0;
09
1<
10
#7
0(
19
0<
08
0'
00
1/
#8
1(
09
1<
10
#9
1%
1&
1K
1A
1@
1J
1?
0B
1>
0C
0D
1I
1=
0E
0F
0G
0H
0L
0M
04
03
02
01
#10
0&
0%
0A
0K
0@
0J
14
#11
1%
1K
1@
1J
0?
04
13
#12
1&
0%
0K
0@
1B
0J
14
#13
0&
1@
1J
1?
0B
0>
0I
04
03
12
#14
1&
0@
1C
0J
14
#15
1&
1D
1@
0C
1J
0?
04
13
#16
0&
0D
0@
0J
14
#17
1%
1K
1@
1J
1?
1>
1I
0=
04
03
02
11
#18
1&
0%
0K
0@
1G
0J
14
#19
1&
1H
1K
1%
1@
0G
1J
0?
1M
04
13
#20
0&
0H
0K
0@
0J
14
#21
1&
1E
1@
1J
1?
0M
0>
0I
1L
04
03
12
#22
0&
0E
0@
0J
14
#23
1@
1J
0?
1M
04
13
#24
1&
0@
1F
0J
14
#25
1$
0#
0+
0*
06
05
#26
0$
1#
1+
#27
0#
0+
1*
#28
1+
#29
1#
0+
0*
16
#30
1+
#31
0+
1*
#32
1+
#33
1$
0#
0+
0*
06
15
#34
1#
1+
#35
0#
0+
1*
#36
1#
1+
#37
1$
0+
0*
16
#38
1+
#39
0+
1*
#40
0$
1+
#41
1!
1"
0.
0-
0,
#42
0!
1.
#43
0"
1!
0.
1-
#44
1"
1.
#45
0!
0.
0-
1,
#46
1.
#47
0"
1!
0.
1-
#48
1"
1.
