Tabla03POS/Tabla03POS_tb.v
//Tabla03POS
//Pablo Moreno carne 19034

module Tabla03POS();

//definir cables

wire N1, N2, N3, N4; //cuatro compuertas NOT
wire A1, A2, A3, A4, A5, A6, A7, A8, A9, out; //una compuerta final AND, compuesta de siete entradas OR


//Declaracion de entradas
reg A, B, C, D;

//Compuertas

not NOA(N1, A); // Negacion de A con compuerta not
not NOB(N2, B); // Negacion de B con compuerta not
not NOC(N3, C); // Negacion de C con compuerta not
not NOD(N4, D); //Negacion de D con compuerta not
or o1(A1, A, N2, C, D); //Primera compuerta or
or o2(A2, A, N2, C, N4); //Segunda compuerta or
or o3(A3, A, N2, N3, D); //tercera compuerta or
or o4(A4, A, N2, N3, N4); //Cuarta compuerta or
or o5(A5, N1, B, C, N4); //Quinta compuerta or
or o6(A6, N1, B, N3, N4); //Sexta compuerta or
or o7(A7, N2, N2, C, D); //Septima compuerta or
or o8(A8, N1, N2, C, N4); //Octava compuerta or
or o9(A9, N1, N2, N3, N4); //Novena compuerta or
and y(out, A1, A2, A3, A4 ,A5, A6, A7, A8, A9); // Ultima compuerta de salida and

initial begin
  $display("A B C D/ Y");
  $display("-------");
  $monitor("%b %b %b %b/ %b", A, B, C, D, out); //para poder ver la tabla de verdad

  //entradas de los modulos
  A = 0; B = 0; C = 0; D=0; //las entradas comienzan en 0
  #1 D=1; //en la segunda fila de la tabla de verdad, D cambia a 1
  #1 C=1; D=0;
  #1 D=1;
  #1 B=1; C=0; D=0;
  #1 D=1;
  #1 C=1; D=0;
  #1 D=1;
  #1 A=1; B=0; C=0; D=0;
  #1 D=1;
  #1 C=1; D=0;
  #1 D=1;
  #1 B=1; C=0; D=0;
  #1 D=1;
  #1 C=1; D=0;
  #1 D=1;
  #1 $finish; //fin de las posibles combinaciones de la tabla de verdad
end

initial begin
  $dumpfile("Tabla03POS_tb.vcd"); //nombre archivo
  $dumpvars(0,Tabla03POS); //nombre del documento
end

endmodule

lab03/Tabla03POS/Tabla03POS_tb.vcd
$date
	Sun Aug 09 15:51:18 2020
$end
$version
	Icarus Verilog
$end
$timescale
	1ps
$end
$scope module Tabla03POS $end
$var wire 1 ! A1 $end
$var wire 1 " A2 $end
$var wire 1 # A3 $end
$var wire 1 $ A4 $end
$var wire 1 % A5 $end
$var wire 1 & A6 $end
$var wire 1 ' A7 $end
$var wire 1 ( A8 $end
$var wire 1 ) A9 $end
$var wire 1 * N1 $end
$var wire 1 + N2 $end
$var wire 1 , N3 $end
$var wire 1 - N4 $end
$var wire 1 . out $end
$var reg 1 / A $end
$var reg 1 0 B $end
$var reg 1 1 C $end
$var reg 1 2 D $end
$upscope $end
$enddefinitions $end
#0
$dumpvars
02
01
00
0/
1.
1-
1,
1+
1*
1)
1(
1'
1&
1%
1$
1#
1"
1!
$end
#1
0-
12
#2
1-
0,
02
11
#3
0-
12
#4
0.
1-
0'
1"
0!
1,
0+
02
01
10
#5
0"
1'
1!
0-
12
#6
0#
1-
1"
0,
02
11
#7
0$
1#
0-
12
#8
1.
1-
1,
1&
1%
1+
1$
0*
02
01
00
1/
#9
0.
0%
0-
12
#10
1.
1-
1%
0,
02
11
#11
0.
0&
0-
12
#12
1-
1(
0'
1,
1&
0+
02
01
10
#13
0(
1'
0-
12
#14
1.
1-
1(
0,
02
11
#15
0.
0)
0-
12
