Lab05/lab05.v
//Mux 2:1
module mux2(
  input wire  D0, D1,
  input wire S,
  output wire Y);
assign Y = S ? D1: D0;

endmodule //module mux2

//Mux 4:1
module mux4 (
  input wire D0 , D1, D2, D3, S0, S1,
  output wire Y1);

  wire W1, W2;

  //Hay que relacionarlo con mux2
  mux2 box1(D0, D1, S0, W1);
  mux2 box2(D2, D3, S0, W2);
  mux2 box3(W1, W2, S1, Y1);

endmodule // mux4

//Mux 8:1
module mux8 (
  input wire D0, D1, D2, D3, D4, D5, D6, D7, S0, S1, S2,
  output wire Y2);

wire W1, W2;

//Ahora se hace una relacion de dos mux 4 y un mux 2
mux4 box1(D0, D1, D2, D3, S0, S1, W1);
mux4 box2(D4, D5, D6, D7, S0, S1, W2);
mux2 box3(W1, W2, S2, Y2); //aqui se utiliza un mux 2 para unificar los muxes 4

endmodule // mux8

module Tabla1_8 (input wire A, B, C, output wire Y);

  wire G, V; //G es 0 porque es tierra y V es 1 porque es voltaje
  assign G = 0;
  assign V = 1;

  mux8 T1_8(G, V, V, G, V, G, G, V, A, B, C, Y);

endmodule // Tabla1_8

//Implementacion de mux 4:1 en tabla 1
module Tabla1_4 (input wire A, B, C, output wire Y);

  wire Cs, CNO; //son las entradas C normal y la C negada

  assign Cs = C;
  assign CNO = ~C;

  mux4 T1_4(Cs, CNO, CNO, Cs, A, B, Y);

endmodule // Tabla1_4

//Implementacion de mux 2:1 en tabla 1
module Tabla1_2 (input wire A, B, C, output wire Y);

  wire B0, C0; //En el dibujo del 2:1 sus entradas son B y C

  assign B0 = (B ^ C);
  assign C0 = ~(B ^ C);

  mux2 T1_2(B0, C0, A, Y);

endmodule // Tabla1_2

//Se va a implementar la tabla 2 con los muxes
module Tabla2_8 (input wire A, B, C, output Y);

wire G, V;

  assign G = 0;
  assign V = 1;

//implementacion del modulo mux8
mux8 T2_8(V, G, G, G, G, V, V, G, A, B, C, Y);

endmodule // Tabla2_8

//mux4


//implementacion del modulo mux4

Lab05/Lab05_tb.v
module testbench();

reg p1, p2, p3, p4, p5, p6, p7, p8, p9;
wire y1, y2, y3;

Tabla1_8 T1_8(p1, p2, p3, y1);

initial begin
#1
$display("\n");
$display("Tabla 1 8:1");
$display("A B C | Y");
$display("------|--");
$monitor("%b %b %b | %b", p1, p2, p3, y1);
     p1 = 0; p2 = 0; p3 = 0;
  #1 p1 = 0; p2 = 0; p3 = 1;
  #1 p1 = 0; p2 = 1; p3 = 0;
  #1 p1 = 0; p2 = 1; p3 = 1;
  #1 p1 = 1; p2 = 0; p3 = 0;
  #1 p1 = 1; p2 = 0; p3 = 1;
  #1 p1 = 1; p2 = 1; p3 = 0;
  #1 p1 = 1; p2 = 1; p3 = 1;
end

Tabla1_4 T1_4(p4, p5, p6, y2);

initial begin
#10
$display("\n");
$display("Tabla 1 4:1");
$display("A B C | Y");
$display("------|--");
$monitor("%b %b %b | %b", p4, p5, p6, y2);
     p4 = 0; p5 = 0; p6 = 0;
  #1 p4 = 0; p5 = 0; p6 = 1;
  #1 p4 = 0; p5 = 1; p6 = 0;
  #1 p4 = 0; p5 = 1; p6 = 1;
  #1 p4 = 1; p5 = 0; p6 = 0;
  #1 p4 = 1; p5 = 0; p6 = 1;
  #1 p4 = 1; p5 = 1; p6 = 0;
  #1 p4 = 1; p5 = 1; p6 = 1;
end

Tabla1_2 T1_2(p7, p8, p9, y3);

initial begin
#20
$display("\n");
$display("Tabla 1 4:1");
$display("A B C | Y");
$display("------|--");
$monitor("%b %b %b | %b", p7, p8, p9, y3);
     p7 = 0; p8 = 0; p9 = 0;
  #1 p7 = 0; p8 = 0; p9 = 1;
  #1 p7 = 0; p8 = 1; p9 = 0;
  #1 p7 = 0; p8 = 1; p9 = 1;
  #1 p7 = 1; p8 = 0; p9 = 0;
  #1 p7 = 1; p8 = 0; p9 = 1;
  #1 p7 = 1; p8 = 1; p9 = 0;
  #1 p7 = 1; p8 = 1; p9 = 1;
end


initial
  #50 $finish;

  initial begin
    $dumpfile("lab05_tb.vcd");
    $dumpvars(0, testbench);
  end

endmodule

Lab05/lab05_tb.vcd
$date
	Sun Aug 16 00:03:15 2020
$end
$version
	Icarus Verilog
$end
$timescale
	1ps
$end
$scope module testbench $end
$var wire 1 ! y3 $end
$var wire 1 " y2 $end
$var wire 1 # y1 $end
$var reg 1 $ p1 $end
$var reg 1 % p2 $end
$var reg 1 & p3 $end
$var reg 1 ' p4 $end
$var reg 1 ( p5 $end
$var reg 1 ) p6 $end
$var reg 1 * p7 $end
$var reg 1 + p8 $end
$var reg 1 , p9 $end
$scope module T1_2 $end
$var wire 1 * A $end
$var wire 1 + B $end
$var wire 1 - B0 $end
$var wire 1 , C $end
$var wire 1 . C0 $end
$var wire 1 ! Y $end
$scope module T1_2 $end
$var wire 1 - D0 $end
$var wire 1 . D1 $end
$var wire 1 * S $end
$var wire 1 ! Y $end
$upscope $end
$upscope $end
$scope module T1_4 $end
$var wire 1 ' A $end
$var wire 1 ( B $end
$var wire 1 ) C $end
$var wire 1 / CNO $end
$var wire 1 0 Cs $end
$var wire 1 " Y $end
$scope module T1_4 $end
$var wire 1 0 D0 $end
$var wire 1 / D1 $end
$var wire 1 / D2 $end
$var wire 1 0 D3 $end
$var wire 1 ' S0 $end
$var wire 1 ( S1 $end
$var wire 1 " Y1 $end
$var wire 1 1 W2 $end
$var wire 1 2 W1 $end
$scope module box1 $end
$var wire 1 0 D0 $end
$var wire 1 / D1 $end
$var wire 1 ' S $end
$var wire 1 2 Y $end
$upscope $end
$scope module box2 $end
$var wire 1 / D0 $end
$var wire 1 0 D1 $end
$var wire 1 ' S $end
$var wire 1 1 Y $end
$upscope $end
$scope module box3 $end
$var wire 1 2 D0 $end
$var wire 1 1 D1 $end
$var wire 1 ( S $end
$var wire 1 " Y $end
$upscope $end
$upscope $end
$upscope $end
$scope module T1_8 $end
$var wire 1 $ A $end
$var wire 1 % B $end
$var wire 1 & C $end
$var wire 1 3 G $end
$var wire 1 4 V $end
$var wire 1 # Y $end
$scope module T1_8 $end
$var wire 1 3 D0 $end
$var wire 1 4 D1 $end
$var wire 1 4 D2 $end
$var wire 1 3 D3 $end
$var wire 1 4 D4 $end
$var wire 1 3 D5 $end
$var wire 1 3 D6 $end
$var wire 1 4 D7 $end
$var wire 1 $ S0 $end
$var wire 1 % S1 $end
$var wire 1 & S2 $end
$var wire 1 # Y2 $end
$var wire 1 5 W2 $end
$var wire 1 6 W1 $end
$scope module box1 $end
$var wire 1 3 D0 $end
$var wire 1 4 D1 $end
$var wire 1 4 D2 $end
$var wire 1 3 D3 $end
$var wire 1 $ S0 $end
$var wire 1 % S1 $end
$var wire 1 6 Y1 $end
$var wire 1 7 W2 $end
$var wire 1 8 W1 $end
$scope module box1 $end
$var wire 1 3 D0 $end
$var wire 1 4 D1 $end
$var wire 1 $ S $end
$var wire 1 8 Y $end
$upscope $end
$scope module box2 $end
$var wire 1 4 D0 $end
$var wire 1 3 D1 $end
$var wire 1 $ S $end
$var wire 1 7 Y $end
$upscope $end
$scope module box3 $end
$var wire 1 8 D0 $end
$var wire 1 7 D1 $end
$var wire 1 % S $end
$var wire 1 6 Y $end
$upscope $end
$upscope $end
$scope module box2 $end
$var wire 1 4 D0 $end
$var wire 1 3 D1 $end
$var wire 1 3 D2 $end
$var wire 1 4 D3 $end
$var wire 1 $ S0 $end
$var wire 1 % S1 $end
$var wire 1 5 Y1 $end
$var wire 1 9 W2 $end
$var wire 1 : W1 $end
$scope module box1 $end
$var wire 1 4 D0 $end
$var wire 1 3 D1 $end
$var wire 1 $ S $end
$var wire 1 : Y $end
$upscope $end
$scope module box2 $end
$var wire 1 3 D0 $end
$var wire 1 4 D1 $end
$var wire 1 $ S $end
$var wire 1 9 Y $end
$upscope $end
$scope module box3 $end
$var wire 1 : D0 $end
$var wire 1 9 D1 $end
$var wire 1 % S $end
$var wire 1 5 Y $end
$upscope $end
$upscope $end
$scope module box3 $end
$var wire 1 6 D0 $end
$var wire 1 5 D1 $end
$var wire 1 & S $end
$var wire 1 # Y $end
$upscope $end
$upscope $end
$upscope $end
$upscope $end
$enddefinitions $end
#0
$dumpvars
x:
x9
x8
x7
x6
x5
14
03
x2
x1
x0
x/
x.
x-
x,
x+
x*
x)
x(
x'
x&
x%
x$
x#
x"
x!
$end
#1
0#
06
15
08
17
1:
09
0&
0%
0$
#2
1#
1&
#3
16
05
0&
1%
#4
0#
1&
#5
1#
18
07
0:
19
0&
0%
1$
#6
0#
1&
#7
06
15
0&
1%
#8
1#
1&
#10
11
1/
0"
02
00
0)
0(
0'
#11
1"
01
12
0/
10
1)
#12
11
02
1/
1"
00
0)
1(
#13
0"
01
12
0/
10
1)
#14
1"
1/
12
00
0)
0(
1'
#15
0"
02
11
0/
10
1)
#16
12
01
1/
0"
00
0)
1(
#17
1"
02
11
0/
10
1)
#20
0!
1.
0-
0,
0+
0*
#21
1!
0.
1-
1,
#22
0,
1+
#23
0!
1.
0-
1,
#24
1!
0,
0+
1*
#25
0!
0.
1-
1,
#26
0,
1+
#27
1!
1.
0-
1,
